tunethresholds/__init__.py
tunethresholds-0.0.1.dist-info/LICENSE
tunethresholds-0.0.1.dist-info/METADATA
tunethresholds-0.0.1.dist-info/WHEEL
tunethresholds-0.0.1.dist-info/top_level.txt
tunethresholds-0.0.1.dist-info/RECORD
